{
	"powers": [
		"touhouorigins:magician/mana",
		"touhouorigins:magician/spells",
		"touhouorigins:magician/spellswitch",
		"touhouorigins:magician/weak_body",
		"touhouorigins:magician/elemental_studies",
		"touhouorigins:magician/automation_studies",
		"touhouorigins:magician/key_check_magician"
	],
	"icon": "minecraft:brown_mushroom",
	"order": 4,
	"impact": 2,
	"upgrades": [
		{
			"condition": "touhouorigins:magi_up_elementalist",
			"origin": "touhouorigins:elementalist",
			"announcement": "origin.touhouorigins.magician.announcementElementalist"
		},
		{
			"condition": "touhouorigins:magi_up_automator",
			"origin": "touhouorigins:automator",
			"announcement": "origin.touhouorigins.magician.announcementAutomator"
		}
	]
}